{
    "sitemap":"yes",
    "meta_data":
    {
        "meta_desc":
        [
			"Le but de ce tutoriel est de vous apprendre",
            "la programmation mobile sous Android.",
            "Produit par Gérard KESSE."
        ],
        "meta_cano":"/Tutoriels/Mobile/Android/",
        "meta_img":"https://raw.githubusercontent.com/gkesse/ReadyDev/master/Tutoriels/Mobile/Android/img/b_android.png"
    },    
    "links":
    [
        {"name":"Tutoriels","link":"/Tutoriels/","follow":"no"},
        {"name":"Mobile","link":"/Tutoriels/#Développement Mobile","follow":"no"},
        {"name":"Android","link":"","follow":"no"}
    ]
}
                        