{
    "sitemap":"yes",
    "meta_data":
    {
        "meta_desc":
        [
            "Le C++ est un langage de programmation orientée objet.",
			"Le but de ce tutoriel est de vous apprendre le C++" 
        ],
        "meta_cano":"/Tutoriels/Cpp/"
    },    
    "links":
    [
        {"name":"Tutoriels","link":"/Tutoriels/"},
        {"name":"C/C++","link":""}
    ],
    "summary":
    [
        {"name":"Apprendre le C++","link":"/Tutoriels/Cpp/Cpp/","follow":"yes"},
        {"name":"Apprendre à compiler un projet C++ avec MinGW","link":"/Tutoriels/Cpp/MinGW/","follow":"yes"}
    ],
    "summary_02":
    [
        {"name":"Apprendre les patrons de conception en C++","link":"/Tutoriels/Cpp/Patrons_Conception/","follow":"yes"}
    ]
}
                        