{
    "sitemap":"yes",
    "meta_data":
    {
        "meta_desc":
        [
			"Le but de ce tutoriel est de vous apprendre",
            "à créer un projet en Pyhton.",
            "Produit par Gérard KESSE."
        ],
        "meta_cano":"/Tutoriels/Pyhton/Cours/Project/",
        "meta_img":"https://raw.githubusercontent.com/gkesse/ReadyDev/master/Tutoriels/Python/img/b_cours_project.png"
    },    
    "links":
    [
        {"name":"Tutoriels","link":"/Tutoriels/#Développement Logiciel","follow":"no"},
        {"name":"Python","link":"/Tutoriels/Python/","follow":"no"},
        {"name":"Cours","link":"/Tutoriels/Python/#Programmation de base","follow":"no"},
        {"name":"Projet","link":"","follow":"no"}
    ]
}
                        